pyetcd3/__init__.py
pyetcd3/client.py
pyetcd3/events.py
pyetcd3/exceptions.py
pyetcd3/leases.py
pyetcd3/locks.py
pyetcd3/members.py
pyetcd3/transactions.py
pyetcd3/utils.py
pyetcd3/watch.py
pyetcd3/etcdrpc/__init__.py
pyetcd3/etcdrpc/auth_pb2.py
pyetcd3/etcdrpc/auth_pb2.pyi
pyetcd3/etcdrpc/kv_pb2.py
pyetcd3/etcdrpc/kv_pb2.pyi
pyetcd3/etcdrpc/rpc_pb2.py
pyetcd3/etcdrpc/rpc_pb2.pyi
pyetcd3/etcdrpc/rpc_pb2_grpc.py
pyetcd3/proto/auth.proto
pyetcd3/proto/kv.proto
pyetcd3/proto/rpc.proto
pyetcd3_sdk-1.0.0.dist-info/licenses/AUTHORS.rst
pyetcd3_sdk-1.0.0.dist-info/licenses/LICENSE
pyetcd3_sdk-1.0.0.dist-info/METADATA
pyetcd3_sdk-1.0.0.dist-info/WHEEL
pyetcd3_sdk-1.0.0.dist-info/top_level.txt
pyetcd3_sdk-1.0.0.dist-info/RECORD
