Metadata-Version: 2.4
Name: pyetcd3-sdk
Version: 1.0.0
Summary: Python client for the etcd v3 API for python >= 3.7
Author-email: wwyoyo03 <wwyoyo03@gmail.com>
Project-URL: Homepage, https://github.com/wwyoyo03/pyetcd3
Project-URL: Docs: User Guide, https://pyetcd3-doc.readthedocs.io/en/latest/
Project-URL: Source Code, https://github.com/wwyoyo03/pyetcd3
Classifier: Programming Language :: Python :: 3
Classifier: License :: OSI Approved :: Apache Software License
Classifier: Operating System :: OS Independent
Requires-Python: >=3.7
License-File: LICENSE
License-File: AUTHORS.rst
Requires-Dist: grpcio<=1.43.0,>=1.41.0
Requires-Dist: protobuf>=4.25.8
Provides-Extra: docs
Requires-Dist: sphinx; extra == "docs"
Requires-Dist: sphinx-rtd-theme; extra == "docs"
Requires-Dist: sphinx-copybutton; extra == "docs"
Requires-Dist: myst-parser; extra == "docs"
Dynamic: license-file
